
{
  "header": {
    "event": "Allocation failed - JavaScript heap out of memory",
    "trigger": "FatalError",
    "filename": "report.20190509.193226.2711.0.001.json",
    "dumpEventTime": "2019-05-09T19:32:26Z",
    "dumpEventTimeStamp": "1557423146645",
    "processId": 2711,
    "cwd": "/home/michele/Documenti/GIT/Algoritmi/esercizio3/svoglimento",
    "commandLine": [
      "/usr/bin/node",
      "/home/michele/Documenti/GIT/Algoritmi/esercizio3/svoglimento/index.js",
      "--stack-size=999999999999999999"
    ],
    "nodejsVersion": "v11.14.0",
    "glibcVersionRuntime": "2.29",
    "glibcVersionCompiler": "2.28",
    "wordSize": 64,
    "arch": "x64",
    "platform": "linux",
    "componentVersions": {
      "node": "11.14.0",
      "v8": "7.0.276.38-node.18",
      "uv": "1.28.0",
      "zlib": "1.2.11",
      "brotli": "1.0.7",
      "ares": "1.15.0",
      "modules": "67",
      "nghttp2": "1.36.0",
      "napi": "4",
      "llhttp": "1.1.1",
      "http_parser": "2.8.0",
      "openssl": "1.1.1b",
      "cldr": "35.1",
      "icu": "64.1",
      "tz": "2019a",
      "unicode": "12.0"
    },
    "release": {
      "name": "node",
      "headersUrl": "https://nodejs.org/download/release/v11.14.0/node-v11.14.0-headers.tar.gz",
      "sourceUrl": "https://nodejs.org/download/release/v11.14.0/node-v11.14.0.tar.gz"
    },
    "osName": "Linux",
    "osRelease": "4.19.36-1-MANJARO",
    "osVersion": "#1 SMP PREEMPT Sat Apr 20 22:05:46 UTC 2019",
    "osMachine": "x86_64",
    "host": "Michele-Fisso-MJ"
  },
  "javascriptStack": {
    "message": "No stack.",
    "stack": [
      "Unavailable."
    ]
  },
  "nativeStack": [
    {
      "pc": "0x000055f322169211",
      "symbol": "report::TriggerNodeReport(v8::Isolate*, node::Environment*, char const*, char const*, std::__cxx11::basic_string<char, std::char_traits<char>, std::allocator<char> > const&, v8::Local<v8::String>) [/usr/bin/node]"
    },
    {
      "pc": "0x000055f32205a74f",
      "symbol": "node::OnFatalError(char const*, char const*) [/usr/bin/node]"
    },
    {
      "pc": "0x000055f3221f47b2",
      "symbol": "v8::Utils::ReportOOMFailure(v8::internal::Isolate*, char const*, bool) [/usr/bin/node]"
    },
    {
      "pc": "0x000055f3221f4a0b",
      "symbol": "v8::internal::V8::FatalProcessOutOfMemory(v8::internal::Isolate*, char const*, bool) [/usr/bin/node]"
    },
    {
      "pc": "0x000055f32258c7d3",
      "symbol": " [/usr/bin/node]"
    },
    {
      "pc": "0x000055f32258c914",
      "symbol": " [/usr/bin/node]"
    },
    {
      "pc": "0x000055f32259c4c6",
      "symbol": "v8::internal::Heap::PerformGarbageCollection(v8::internal::GarbageCollector, v8::GCCallbackFlags) [/usr/bin/node]"
    },
    {
      "pc": "0x000055f32259ce6e",
      "symbol": "v8::internal::Heap::CollectGarbage(v8::internal::AllocationSpace, v8::internal::GarbageCollectionReason, v8::GCCallbackFlags) [/usr/bin/node]"
    },
    {
      "pc": "0x000055f32259f06d",
      "symbol": "v8::internal::Heap::AllocateRawWithLightRetry(int, v8::internal::AllocationSpace, v8::internal::AllocationAlignment) [/usr/bin/node]"
    },
    {
      "pc": "0x000055f32259f0c2",
      "symbol": "v8::internal::Heap::AllocateRawWithRetryOrFail(int, v8::internal::AllocationSpace, v8::internal::AllocationAlignment) [/usr/bin/node]"
    },
    {
      "pc": "0x000055f32256da05",
      "symbol": "v8::internal::Factory::NewFillerObject(int, bool, v8::internal::AllocationSpace) [/usr/bin/node]"
    },
    {
      "pc": "0x000055f3227dc2af",
      "symbol": "v8::internal::Runtime_AllocateInNewSpace(int, v8::internal::Object**, v8::internal::Isolate*) [/usr/bin/node]"
    },
    {
      "pc": "0x000020eb5ae4fc5d",
      "symbol": ""
    }
  ],
  "javascriptHeap": {
    "totalMemory": 1506213888,
    "totalCommittedMemory": 1498388448,
    "usedMemory": 1470049072,
    "availableMemory": 25340880,
    "memoryLimit": 1526909922,
    "heapSpaces": {
      "read_only_space": {
        "memorySize": 524288,
        "committedMemory": 42224,
        "capacity": 515584,
        "used": 33520,
        "available": 482064
      },
      "new_space": {
        "memorySize": 10485760,
        "committedMemory": 3758960,
        "capacity": 5155840,
        "used": 1103288,
        "available": 4052552
      },
      "old_space": {
        "memorySize": 1435176960,
        "committedMemory": 1434954080,
        "capacity": 1411342952,
        "used": 1411040752,
        "available": 302200
      },
      "code_space": {
        "memorySize": 1048576,
        "committedMemory": 854368,
        "capacity": 572480,
        "used": 572480,
        "available": 0
      },
      "map_space": {
        "memorySize": 536576,
        "committedMemory": 337088,
        "capacity": 246960,
        "used": 246960,
        "available": 0
      },
      "large_object_space": {
        "memorySize": 58441728,
        "committedMemory": 58441728,
        "capacity": 77556136,
        "used": 57052072,
        "available": 20504064
      },
      "new_large_object_space": {
        "memorySize": 0,
        "committedMemory": 0,
        "capacity": 0,
        "used": 0,
        "available": 0
      }
    }
  },
  "resourceUsage": {
    "userCpuSeconds": 16.722,
    "kernelCpuSeconds": 0.362025,
    "cpuConsumptionPercent": 170.84,
    "maxRss": 1555636224,
    "pageFaults": {
      "IORequired": 0,
      "IONotRequired": 427686
    },
    "fsActivity": {
      "reads": 0,
      "writes": 0
    }
  },
  "uvthreadResourceUsage": {
    "userCpuSeconds": 7.32763,
    "kernelCpuSeconds": 0.312261,
    "cpuConsumptionPercent": 76.3989,
    "fsActivity": {
      "reads": 0,
      "writes": 0
    }
  },
  "libuv": [
  ],
  "environmentVariables": {
    "PATH": "/usr/local/sbin:/usr/local/bin:/usr/bin:/var/lib/flatpak/exports/bin:/opt/flutter/bin:/usr/lib/jvm/default/bin:/usr/bin/site_perl:/usr/bin/vendor_perl:/usr/bin/core_perl:/var/lib/snapd/snap/bin",
    "LC_MEASUREMENT": "it_IT.UTF-8",
    "XAUTHORITY": "/home/michele/.Xauthority",
    "LC_TELEPHONE": "it_IT.UTF-8",
    "XDG_DATA_DIRS": "/home/michele/.local/share/flatpak/exports/share:/var/lib/flatpak/exports/share:/usr/local/share:/usr/share:/var/lib/snapd/desktop",
    "LC_TIME": "it_IT.UTF-8",
    "DBUS_SESSION_BUS_ADDRESS": "unix:path=/run/user/1000/bus",
    "XDG_CURRENT_DESKTOP": "KDE",
    "QT_AUTO_SCREEN_SCALE_FACTOR": "0",
    "MAIL": "/var/spool/mail/michele",
    "MOZ_PLUGIN_PATH": "/usr/lib/mozilla/plugins",
    "COLORTERM": "true",
    "QT_LINUX_ACCESSIBILITY_ALWAYS_ON": "1",
    "LC_PAPER": "it_IT.UTF-8",
    "SESSION_MANAGER": "local/Michele-Fisso-MJ:@/tmp/.ICE-unix/1194,unix/Michele-Fisso-MJ:/tmp/.ICE-unix/1194",
    "LOGNAME": "michele",
    "PAM_KWALLET5_LOGIN": "/run/user/1000/kwallet5.socket",
    "PWD": "/home/michele/Documenti/GIT/Algoritmi/esercizio3/svoglimento",
    "XCURSOR_THEME": "breeze_cursors",
    "LANGUAGE": "",
    "KDE_SESSION_VERSION": "5",
    "SHELL": "/bin/bash",
    "LC_ADDRESS": "it_IT.UTF-8",
    "QT_SCREEN_SCALE_FACTORS": "DisplayPort-0=1.4;DisplayPort-1=1.4;HDMI-0=1.4;DVI-0=1.4;DVI-1=1.4;",
    "OLDPWD": "/home/michele/.local/share/JetBrains/Toolbox/apps/IDEA-JDK11/ch-0/191.6707.61/bin",
    "KDE_FULL_SESSION": "true",
    "GTK_MODULES": "canberra-gtk-module",
    "XDG_SESSION_PATH": "/org/freedesktop/DisplayManager/Session1",
    "XDG_SESSION_DESKTOP": "KDE",
    "SHLVL": "2",
    "LC_IDENTIFICATION": "it_IT.UTF-8",
    "LC_MONETARY": "it_IT.UTF-8",
    "FORCE_COLOR": "true",
    "ELECTRON_NO_ATTACH_CONSOLE": "true",
    "KDE_SESSION_UID": "1000",
    "FLUTTER_HOME": "/opt/flutter",
    "XDG_SEAT_PATH": "/org/freedesktop/DisplayManager/Seat0",
    "LANG": "it_IT.UTF-8",
    "DEBUG_COLORS": "true",
    "XDG_SESSION_ID": "2",
    "XDG_SESSION_TYPE": "x11",
    "npm_config_color": "always",
    "DISPLAY": ":0",
    "MOCHA_COLORS": "1",
    "LC_NAME": "it_IT.UTF-8",
    "_": "/home/michele/.local/share/JetBrains/Toolbox/apps/IDEA-JDK11/ch-0/191.6707.61/jre64/bin/java",
    "XDG_SESSION_CLASS": "user",
    "DESKTOP_SESSION": "/usr/share/xsessions/plasma",
    "USER": "michele",
    "DESKTOP_STARTUP_ID": "Michele-Fisso-MJ;1557422818;171670;1218_TIME449278",
    "DEBUG": "svoglimento:*",
    "LC_NUMERIC": "it_IT.UTF-8",
    "XDG_SEAT": "seat0",
    "GS_LIB": "/home/michele/.fonts",
    "XDG_RUNTIME_DIR": "/run/user/1000",
    "XDG_VTNR": "1",
    "HOME": "/home/michele"
  },
  "userLimits": {
    "core_file_size_blocks": {
      "soft": "unlimited",
      "hard": "unlimited"
    },
    "data_seg_size_kbytes": {
      "soft": "unlimited",
      "hard": "unlimited"
    },
    "file_size_blocks": {
      "soft": "unlimited",
      "hard": "unlimited"
    },
    "max_locked_memory_bytes": {
      "soft": 65536,
      "hard": 65536
    },
    "max_memory_size_kbytes": {
      "soft": "unlimited",
      "hard": "unlimited"
    },
    "open_files": {
      "soft": 1048576,
      "hard": 1048576
    },
    "stack_size_bytes": {
      "soft": 8388608,
      "hard": "unlimited"
    },
    "cpu_time_seconds": {
      "soft": "unlimited",
      "hard": "unlimited"
    },
    "max_user_processes": {
      "soft": 62951,
      "hard": 62951
    },
    "virtual_memory_kbytes": {
      "soft": "unlimited",
      "hard": "unlimited"
    }
  },
  "sharedObjects": [
    "linux-vdso.so.1",
    "/usr/lib/libz.so.1",
    "/usr/lib/libuv.so.1",
    "/usr/lib/libcares.so.2",
    "/usr/lib/libnghttp2.so.14",
    "/usr/lib/libcrypto.so.1.1",
    "/usr/lib/libssl.so.1.1",
    "/usr/lib/libicui18n.so.64",
    "/usr/lib/libicuuc.so.64",
    "/usr/lib/libdl.so.2",
    "/usr/lib/librt.so.1",
    "/usr/lib/libstdc++.so.6",
    "/usr/lib/libm.so.6",
    "/usr/lib/libgcc_s.so.1",
    "/usr/lib/libpthread.so.0",
    "/usr/lib/libc.so.6",
    "/usr/lib/libnsl.so.2",
    "/usr/lib/libicudata.so.64",
    "/lib64/ld-linux-x86-64.so.2",
    "/usr/lib/libtirpc.so.3",
    "/usr/lib/libgssapi_krb5.so.2",
    "/usr/lib/libkrb5.so.3",
    "/usr/lib/libk5crypto.so.3",
    "/usr/lib/libcom_err.so.2",
    "/usr/lib/libkrb5support.so.0",
    "/usr/lib/libkeyutils.so.1",
    "/usr/lib/libresolv.so.2"
  ]
}